.gitignore
MANIFEST.in
Makefile
README.md
optional-requirements.txt
requirements.txt
setup.py
docs/LIFECYCLE.md
examples/__init__.py
examples/basic/__init__.py
examples/basic/demo.py
examples/basic/demo_components/__init__.py
examples/basic/demo_components/demo_base.py
examples/basic/demo_components/DemoComponent/DemoComponent.js
examples/basic/demo_components/DemoComponent/DemoComponent.mustache
examples/basic/demo_components/DemoComponent/DemoComponent.sass
examples/basic/demo_components/DemoComponent/__init__.py
examples/basic/demo_components/DemoPage/DemoPage.js
examples/basic/demo_components/DemoPage/__init__.py
examples/basic/templates/example.html
examples/basic/templates/layout.html
examples/blank/__init__.py
examples/blank/web.py
examples/pagelet/__init__.py
examples/pagelet/demo.py
examples/pagelet/demo_components/__init__.py
examples/pagelet/demo_components/demo_base.py
examples/pagelet/demo_components/DemoComponent/DemoComponent.js
examples/pagelet/demo_components/DemoComponent/DemoComponent.mustache
examples/pagelet/demo_components/DemoComponent/DemoComponent.sass
examples/pagelet/demo_components/DemoComponent/__init__.py
examples/pagelet/demo_components/DemoPage/DemoPage.js
examples/pagelet/demo_components/DemoPage/__init__.py
examples/pagelet/templates/example.html
examples/pagelet/templates/layout.html
examples/react/__init__.py
examples/react/demo.py
examples/react/demo_components/__init__.py
examples/react/demo_components/demo_base.py
examples/react/demo_components/DemoComponent/DemoComponent.jsx
examples/react/demo_components/DemoComponent/DemoComponent.sass
examples/react/demo_components/DemoComponent/__init__.py
examples/react/demo_components/DemoComponent/external_renderer.jsx
examples/react/demo_components/DemoPage/DemoPage.js
examples/react/demo_components/DemoPage/__init__.py
examples/react/static/my-react.js
examples/react/templates/example.html
examples/react/templates/layout.html
examples/require_css/__init__.py
pudgy.egg-info/PKG-INFO
pudgy.egg-info/SOURCES.txt
pudgy.egg-info/dependency_links.txt
pudgy.egg-info/requires.txt
pudgy.egg-info/top_level.txt
