Metadata-Version: 1.0
Name: pudgy
Version: 0.2.2
Summary: a component library for flask
Home-page: http://github.com/logv/pudgy
Author: okay
Author-email: okayzed+pudgy@gmail.com
License: MIT
Platform: UNKNOWN
